[{"__symbolic":"module","version":4,"metadata":{"AccountPickerComponent":{"__symbolic":"class","decorators":[{"__symbolic":"call","expression":{"__symbolic":"reference","module":"@angular/core","name":"Component"},"arguments":[{"selector":"account-picker","templateUrl":"account-picker.html","providers":[{"provide":{"__symbolic":"reference","module":"@angular/forms","name":"NG_VALUE_ACCESSOR"},"useExisting":{"__symbolic":"reference","name":"AccountPickerComponent"},"multi":true}]}]}],"members":{"__ctor__":[{"__symbolic":"constructor","parameters":[{"__symbolic":"reference","module":"ionic-angular","name":"ModalController"},{"__symbolic":"reference","module":"ionic-angular","name":"NavController"},{"__symbolic":"reference","module":"../../StoreData/accounts-fb-repository","name":"AccountsFsRepository"}]}],"writeValue":[{"__symbolic":"method"}],"removeAccountInfo":[{"__symbolic":"method"}],"selectAccountInfo":[{"__symbolic":"method"}],"registerOnChange":[{"__symbolic":"method"}],"registerOnTouched":[{"__symbolic":"method"}],"setDisabledState":[{"__symbolic":"method"}]}}}}]